orangeqt
