Metadata-Version: 1.0
Name: qt-graph-helpers
Version: 0.1.1
Summary: PyQt Graph Primitives for Orange
Home-page: http://orange.biolab.si
Author: Bioinformatics Laboratory, FRI UL
Author-email: orange@fri.uni-lj.si
License: GNU General Public License (GPL)
Platform: UNKNOWN
